LICENSE
pygitm/__init__.py
pygitm/auth.py
pygitm/constants.py
pygitm/git.py
pygitm/options.py
pygitm/repository.py
pygitm/workspace.py
pygitm-0.10.1.dist-info/LICENSE
pygitm-0.10.1.dist-info/WHEEL
pygitm-0.10.1.dist-info/METADATA
pygitm-0.10.1.dist-info/RECORD
